memealerts/__init__.py
memealerts/base_client.py
memealerts/async_cli/__init__.py
memealerts/async_cli/client.py
memealerts/sync_cli/__init__.py
memealerts/sync_cli/client.py
memealerts/types/__init_.py
memealerts/types/__init__.py
memealerts/types/dicts.py
memealerts/types/encoder.py
memealerts/types/exceptions.py
memealerts/types/models.py
memealerts/types/user_id.py
memealerts/utils/.gitkeep
memealerts-1.1.3.dist-info/METADATA
memealerts-1.1.3.dist-info/WHEEL
memealerts-1.1.3.dist-info/licenses/LICENSE.txt
memealerts-1.1.3.dist-info/RECORD
