Metadata-Version: 2.4
Name: memealerts
Version: 1.1.3
Summary: Memealerts async/sync client
Project-URL: Author's Twitch, https://www.twitch.tv/quantum075
Author-email: Anton Kurenkov <quantum0@mail.ru>
Maintainer-email: Anton Kurenkov <quantum0@mail.ru>
License-Expression: MIT
License-File: LICENSE.txt
Keywords: meme,memealert,memealerts,memes,twitch
Classifier: Development Status :: 2 - Pre-Alpha
Classifier: Operating System :: OS Independent
Classifier: Programming Language :: Python :: 3 :: Only
Classifier: Topic :: Software Development :: Libraries :: Python Modules
Requires-Python: >=3.11
Requires-Dist: httpx>=0.28.1
Requires-Dist: pydantic>=2.11.7
Requires-Dist: pyjwt>=2.10.1
Requires-Dist: requests>=2.32.4
Provides-Extra: test
Requires-Dist: pre-commit==4.2.0; extra == 'test'
Requires-Dist: pytest-env==1.1.5; extra == 'test'
Requires-Dist: ruff==4.2.0; extra == 'test'
